Betelgeuse/__init__.py
Betelgeuse/__version__.py
Betelgeuse/betelgeuse.py
Betelgeuse/exceptions.py
Betelgeuse/input.py
Betelgeuse/logging.py
strobes_betelgeuse-1.0.dist-info/LICENSE
strobes_betelgeuse-1.0.dist-info/METADATA
strobes_betelgeuse-1.0.dist-info/WHEEL
strobes_betelgeuse-1.0.dist-info/entry_points.txt
strobes_betelgeuse-1.0.dist-info/top_level.txt
strobes_betelgeuse-1.0.dist-info/RECORD
