Metadata-Version: 2.1
Name: strobes-betelgeuse
Version: 1.0
Summary: Betelgeuse is a wrapper for Strobes API that helps you integrate scans into your CI/CD easily.
Home-page: https://strobes.co/
Author: Akhil Reni
Author-email: akhil@wesecureapp.com
License: GPLv3
Platform: UNKNOWN
Requires-Python: >=3.6
